Workbook

Sheet Расчёт стоимости этикетки
A2: Р краски | C2: ='Расход краски'!C22 | E2: время настройки на цвет мин | H2: 10
A3: P материала | C3: ='расход бумаги'!G9 | E3: время настройки на нож мин | H3: 5
A4: T Тираж | C4: ='расход бумаги'!C7 | E4: время настройки общее ч | H4: =((C8*H2)+H3)/60
A5: Затраты материалов на этикетку | C5: =(C2+C3)/C4 | E5: время печати ч | H5: ='расход бумаги'!C8/(C6*60)
A6: Скорость печати м/мин | C6: 30 | E6: перемотка и упаковка ч | H6: ='расход бумаги'!C8/(C7*60)
A7: Скорость перемотки м/мин | C7: 50
A8: Количество цветов | C8: =(IF('Расход краски'!C4>0,1,0) + IF('Расход краски'!D4>0,1,0) + IF('Расход краски'!E4>0,1,0) + IF('Расход краски'!F4>0,1,0) + IF('Расход краски'!C10>0,1,0) + IF('Расход краски'!D10>0,1,0) + IF('Расход краски'!E10>0,1,0) + IF('Расход краски'!F10>0,1,0) + IF('Расход краски'!C16>0,1,0) + IF('Расход краски'!D16>0,1,0) + IF('Расход краски'!E16>0,1,0) + IF('Расход краски'!F16>0,1,0)) | E8: Рабочих дней в месяце | H8: 22
A9: Всего затраты на заказ | C9: =C2+C3+H12 | E9: Норма рабочих часов | H9: 8
A10: Расходная часть | E10: Почасовая стоимость накладных расходов | H10: =C19/(H8*H9)
A11: аренда | C11: 110000
A12: коммунальные платежи | C12: 160000 | E12: Накладные расходы на заказ | H12: =(H4+H5+H6)*H10
A13: развоз продукции | C13: 10000 | E13: Расходы на этикетку | H13: =C9/C4
A14: налоги | C14: 100000 | E14: Markup | H14: =H13*(1+G15)
A15: Обслуживание производства | C15: 30000 | G15: 0.3
A16: Техобслуживание | C16: 30000
A17: Зарплата производство | C17: =(170+150+110+110)*10*24
A18: Зарплата АУП | C18: 310000
A19: Всего | C19: =SUM(C11:C18)

Sheet расход бумаги
C1: х | D1: y | E1: S нетто, м2 | F1: S брутто, м3
B2: Размер этикетки (мм) | C2: 58 | D2: 59 | E2: =C2*D2/1000000 | F2: =C9/C7
B3: ширина материала (мм) | C3: 200 | E3: ширина плёнки для ламинации | F3: 0 | G3: ширина фольги | H3: 0
B4: Вал Z | C4: 96 | D4: А1 | E4: А2
B5: Количество ручьёв | C5: 3 | D5: =(C3-(C2*C5))/2 | E5: =((C4*3.175)-(D2*C6))/C6
B6: Этикеток в ручье | C6: 5
B7: Тираж (шт) | C7: 60000 | D7: Цена материала | E7: Цена ламинаии м2 | F7: Цена фолги м2 | G7: На тираж в рублях
B8: Расход п.м | C8: =(C7*C4*3.175)/(C5*C6*1000)+(C10+C11)/C3*1000
B9: Расход кв.м. | C9: =C8*(C3/1000) | D9: 45 | E9: 11.76 | F9: 19.96 | G9: =C9*D9+(C13*E9)+(C14*F9)
B10: Вырубка, кв.м | C10: 5
B11: Приращение на цвет, кв.м | C11: =( IF('Расход краски'!C4>0,10,0) + IF('Расход краски'!D4>0,10,0) + IF('Расход краски'!E4>0,10,0) + IF('Расход краски'!F4>0,10,0) + IF('Расход краски'!C10>0,10,0) + IF('Расход краски'!D10>0,10,0) + IF('Расход краски'!E10>0,10,0) + IF('Расход краски'!F10>0,10,0) + IF('Расход краски'!C16>0,10,0) + IF('Расход краски'!D16>0,10,0) + IF('Расход краски'!E16>0,10,0) + IF('Расход краски'!F16>0,10,0) )
B13: Ламинация | C13: =F3/1000*C8
B14: Фольга Х/Т | C14: =H3/1000*C8

Sheet Расход краски
B2: F2400 | I2: цвет | J2: цена
B3: триада | C3: С | D3: M | E3: Y | F3: K | I3: С | J3: 1700
B4: Авто: покрытие импортировано скриптом | C4: 0.0741 | D4: 17.9229 | E4: 74.5347 | F4: 24.884 | I4: M | J4: 1700
B5: Анилокс | C5: 400/12 | D5: 400/12 | E5: 400/12 | F5: 400/13 | I5: Y | J5: 1700
B6: на макет кг | C6: =(((C4/100)*(VLOOKUP(C5, Анилоксы!$B$3:$D$17, 2, FALSE)))/1000)*'расход бумаги'!F2 | D6: =(((D4/100)*(VLOOKUP(D5, Анилоксы!$B$3:$D$17, 2, FALSE)))/1000)*'расход бумаги'!F2 | E6: =(((E4/100)*(VLOOKUP(E5, Анилоксы!$B$3:$D$17, 2, FALSE)))/1000)*'расход бумаги'!F2 | F6: =(((F4/100)*(VLOOKUP(F5, Анилоксы!$B$3:$D$17, 2, FALSE)))/1000)*'расход бумаги'!F2 | I6: K | J6: 1900
B7: на тираж кг | C7: =C6*'расход бумаги'!C7 | D7: =D6*'расход бумаги'!C7 | E7: =E6*'расход бумаги'!C7 | F7: =F6*'расход бумаги'!C7 | I7: color1 | J7: 2500
B8: на тираж р | C8: =C7*J3 | D8: =D7*J4 | E8: =E7*J5 | F8: =F7*J6 | I8: color2 | J8: 3000
B9: Pantone | C9: color1 | D9: color2 | E9: color3 | F9: color4 | I9: color3 | J9: 5000
B10: Заливка % | C10: 0 | D10: 0 | E10: 0 | F10: 0 | I10: color4
B11: Анилокс | C11: 120/13 | D11: 100/15 | E11: 100/15 | F11: 100/15 | I11: varnish G | J11: 1200
B12: на макет кг | C12: =(((C10/100)*(VLOOKUP(C11, Анилоксы!$B$3:$D$17, 2, FALSE)))/1000)*'расход бумаги'!F2 | D12: =(((D10/100)*(VLOOKUP(D11, Анилоксы!$B$3:$D$17, 2, FALSE)))/1000)*'расход бумаги'!F2 | E12: =(((E10/100)*(VLOOKUP(E11, Анилоксы!$B$3:$D$17, 2, FALSE)))/1000)*'расход бумаги'!F2 | F12: =(((F10/100)*(VLOOKUP(F11, Анилоксы!$B$3:$D$17, 2, FALSE)))/1000)*'расход бумаги'!F2 | I12: varnish M | J12: 2500
B13: на тираж | C13: =C12*'расход бумаги'!C7 | D13: =D12*'расход бумаги'!C7 | E13: =E12*'расход бумаги'!C7 | F13: =F12*'расход бумаги'!C7 | I13: adh1 | J13: 2000
B14: на тираж р | C14: =C13*J7 | D14: =D13*J8 | E14: =E13*J9 | F14: =F13*J10 | I14: Primer
B15: Лак, клей | C15: varnish G | D15: varnish M | E15: adh1 | F15: primer
B16: Заливка % | C16: 0 | D16: 0 | E16: 0 | F16: 0
B17: Анилокс | C17: 90/19 | D17: 90/19 | E17: 100/15 | F17: 100/15
B18: на макет кг | C18: =(((C16/100)*(VLOOKUP(C17, Анилоксы!$B$3:$D$17, 2, FALSE)))/1000)*'расход бумаги'!F2 | D18: =(((D16/100)*(VLOOKUP(D17, Анилоксы!$B$3:$D$17, 2, FALSE)))/1000)*'расход бумаги'!F2 | E18: =(((E16/100)*(VLOOKUP(E17, Анилоксы!$B$3:$D$17, 2, FALSE)))/1000)*'расход бумаги'!F2 | F18: =((F16/100)*(VLOOKUP(F17, Анилоксы!$B$3:$D$17, 2, FALSE)))/1000*'расход бумаги'!F2
B19: на тираж | C19: =C18*'расход бумаги'!C7 | D19: =D18*'расход бумаги'!C7 | E19: =E18*'расход бумаги'!C7 | F19: =F18*'расход бумаги'!C7
B20: на тираж р | C20: =C19*J11 | D20: =D19*J12 | E20: =E19*J13 | F20: =F19*J14
B21: на макет | C21: =C22/'расход бумаги'!C7
B22: Всего | C22: =C8+D8+E8+F8+C14+D14+E14+F14+C20+D20+E20+F20

Sheet Анилоксы
A1: F2400 | G1: XP5000
A2: № | B2: Линиатур / Объём | C2: перенос в граммах | D2: количество | G2: № | H2: Линиатур / Объём | I2: перенос | J2: Количество
A3: 1 | B3: 100/15 | C3: 5 | D3: 2 | G3: 1 | H3: 200/8,0 | I3: 8.4 | J3: 60
A4: 2 | B4: 120/13 | C4: 4.33 | D4: 1 | G4: 2 | H4: 180/9,0 | I4: 9.45 | J4: 60
A5: 3 | B5: 140/7 | C5: 2.4 | D5: 3 | G5: 3 | H5: 160/9,0 | I5: 9.45 | J5: 60
A6: 4 | B6: 160/6 | C6: 2 | D6: 3 | G6: 4 | H6: 160/10,0 | I6: 10.5 | J6: 60
A7: 5 | B7: 140/11 | C7: 3.7 | D7: 2 | G7: 5 | H7: 120/12,0 | I7: 12.6 | J7: 60
A8: 6 | B8: 140/13 | C8: 4.33 | D8: 1 | G8: 6 | H8: 140/12,0 | I8: 12.6 | J8: 60
A9: 7 | B9: 90/19 | C9: 6.33 | D9: 1 | G9: 7 | H9: 240/7,0 | I9: 7.35 | J9: 60
A10: 8 | B10: 400/12 | C10: 4 | D10: 1 | G10: 8 | H10: 350/4,0 | I10: 4.2 | J10: 60
A11: 9 | B11: 400/13 | C11: 4.33 | D11: 1 | G11: 9 | H11: 320/4,5 | I11: 4.725 | J11: 60
A12: 10 | B12: 450/12 | C12: 4 | D12: 1 | G12: 10 | H12: 280/5,5 | I12: 5.775 | J12: 60
A13: 11 | B13: 500/12 | C13: 4 | D13: 1 | G13: 11 | H13: 240/7,0 | I13: 7.35 | J13: 60
A14: 12 | B14: 400/14 | C14: 4.7 | D14: 1 | G14: 12 | H14: 240/6,4 | I14: 6.72 | J14: 60
... A17: 15 | B17: 110/23 | C17: 41 | D17: 1 | G17: 15 | H17: 500/2,8 | I17: 2.94 | J17: 60
G18: 16 | H18: 350/4,5 | I18: 4.725 | J18: 60
G19: 17 | H19: 350/4,0 | I19: 4.2 | J19: 60

Sheet Прайс
A1: материал | B1: цена за 1 м2 с НДС | C1: доставка | D1: итог
A2: Бумага самоклеящаяся GelioLabel SA L 80 P/H411 P/ Y 58 (каучук) | B2: 31 | C2: 7 | D2: =B2+C2
A3: Бумага самоклеящаяся GelioLabel SA L 80 P /A111 P / Y 58 (акрил) | B3: 31 | C3: 7 | D3: =B3+C3
A4: Пленка самоклеящаяся GelioLabel SA PP 60 White Gloss Cavitated /A110P/W58 | B4: 36 | C4: 9 | D4: =B4+C4
A5: Пленка самоклеящаяся GelioLabel SA PP 60 Solid White Gloss/A110P/ PET 30 | B5: 45 | C5: 9 | D5: =B5+C5
A6: Пленка самоклеящаяся GelioLabel SA PP 60 Clear Gloss/A110P/W58 | B6: 39 | C6: 9 | D6: =B6+C6
A7: Пленка самоклеящаяся GelioLabel SA PP 60 White Gloss Cavitated freezing/FH410P/W58 | B7: 41.5 | C7: 9 | D7: =B7+C7
A8: Пленка самоклеящаяся GelioLabel SA PP 60 Clear Gloss/A110P/ PET 30 | B8: 44 | C8: 9 | D8: =B8+C8
A9: Бумага самоклеящаяся GelioLabel SA Thermal Top 70 freezing/FН411P/Y58 | B9: 36 | C9: 9 | D9: =B9+C9
A10: Бумага самоклеящаяся GelioLabel SA Thеrmal Eco 70/H411P/Y58 | B10: 33 | C10: 9 | D10: =B10+C10
A11: Пленка самоклеящаяся GelioLabel SA Direct Thermal T75 White Gloss freezing/FН410P/W58 | B11: 59 | C11: 9 | D11: =B11+C11
A12: фольга
A13: UNO FOIL CWO AL 3000 м Фольга для холодного тиснения | B13: 14.96 | C13: 5 | D13: =B13+C13
A14: UNO FOIL CWO 220 3000 м Фольга для холодного тиснения | B14: 14.96 | C14: 5 | D14: =B14+C14
A15: UNO FOIL Laser 01 AL CWO 2000 м Фольга для холодного тиснения | B15: 70.9 | C15: 5 | D15: =B15+C15
A16: ламинация
A17: MGRAFO WPM13 матовая 0,013x2000 м Пленка для холодной ламинации | B17: 6.76 | C17: 5 | D17: =B17+C17
A18: MGRAFO WPG12 глянцевая 0,012x2000 м Пленка для холодной ламинации | B18: 7.56 | C18: 5 | D18: =B18+C18
A19: втулки
A20: втулка картонная 15х40
A21: втулка платиковая 40
A22: втулка картонная 76
A23: втулка картонная 152
